{
  "marketplace": "ES",
  "hero_headline": "Motron Care Electrodos TENS/EMS Pro - Electrodos cómodos para el día a día",
  "hero_subtext": "Electrodos de hidrogel amigables con la piel para una estimulación uniforme en casa, en el estudio y en movimiento.",
  "benefit_blocks": [
    {
      "title": "Conductividad constante",
      "text": "Transmisión uniforme de impulsos para una aplicación estable."
    },
    {
      "title": "Suaves sobre la piel",
      "text": "Sensación agradable incluso con uso repetido."
    },
    {
      "title": "Sujeción fiable",
      "text": "Ajuste seguro durante el descanso, el trabajo y el movimiento."
    },
    {
      "title": "Aplicación flexible",
      "text": "Adecuados para cuello, espalda, hombros y piernas."
    }
  ],
  "problem_title": "Las tensiones musculares frenan el día a día",
  "problem_text": "Estar sentado por mucho tiempo, cargas intensas y movimientos repetitivos suelen provocar sensaciones de tensión.",
  "solution_title": "Impulsos dirigidos con un enfoque claro",
  "solution_text": "Los electrodos transmiten impulsos TENS/EMS de manera uniforme y apoyan una rutina de recuperación planificada.",
  "compatibility_points": [
    "Dispositivos TENS con conector de 2 mm",
    "Dispositivos EMS con conector de 2 mm",
    "Muchos sistemas de terapia en casa",
    "Dispositivos de rehabilitación portátiles"
  ],
  "use_case_points": [
    "Recuperación después del entrenamiento",
    "Apoyo para tensiones en cuello y espalda",
    "Alivio tras largas horas sentado",
    "Comodidad durante los viajes"
  ],
  "module_texts": {
    "hero": "Calidad premium para una aplicación fiable en el día a día.",
    "body_mapping": "Cada beneficio apoya un objetivo concreto de comodidad y movimiento.",
    "problem_solution": "De la tensión a la recuperación estructurada en pocos pasos.",
    "features": "Materiales duraderos, fácil manejo y ajuste limpio.",
    "compatibility": "Compatible con muchos dispositivos comunes con conexión de 2 mm."
  },
  "export_text_by_template": {
    "hero": {
      "headline": "Motron Care Electrodos TENS/EMS Pro - Electrodos cómodos para el día a día",
      "subtext": "Electrodos de hidrogel amigables con la piel para una estimulación uniforme en casa, en el estudio y en movimiento."
    },
    "body_mapping": {
      "benefit_1_title": "Conductividad constante",
      "benefit_1_text": "Transmisión uniforme de impulsos para una aplicación estable.",
      "benefit_2_title": "Suaves sobre la piel",
      "benefit_2_text": "Sensación agradable incluso con uso repetido.",
      "benefit_3_title": "Sujeción fiable",
      "benefit_3_text": "Ajuste seguro durante el descanso, el trabajo y el movimiento.",
      "benefit_4_title": "Aplicación flexible",
      "benefit_4_text": "Adecuados para cuello, espalda, hombros y piernas."
    },
    "problem_solution": {
      "problem_title": "Las tensiones musculares frenan el día a día",
      "problem_text": "Estar sentado por mucho tiempo, cargas intensas y movimientos repetitivos suelen provocar sensaciones de tensión.",
      "solution_title": "Impulsos dirigidos con un enfoque claro",
      "solution_text": "Los electrodos transmiten impulsos TENS/EMS de manera uniforme y apoyan una rutina de recuperación planificada."
    },
    "features": {
      "feature_text": "Materiales duraderos, fácil manejo y ajuste limpio."
    },
    "compatibility": {
      "compatibility": "Dispositivos TENS con conector de 2 mm | Dispositivos EMS con conector de 2 mm | Muchos sistemas de terapia en casa | Dispositivos de rehabilitación portátiles",
      "use_cases": "Recuperación después del entrenamiento | Apoyo para tensiones en cuello y espalda | Alivio tras largas horas sentado | Comodidad durante los viajes"
    }
  }
}